LICENSE
MANIFEST.in
README.md
requirements_dev.txt
setup.cfg
setup.py
deeprenewal/__init__.py
deeprenewal/_datasets.py
deeprenewal/_evaluator.py
deeprenewal/cli.py
deeprenewal.egg-info/PKG-INFO
deeprenewal.egg-info/SOURCES.txt
deeprenewal.egg-info/dependency_links.txt
deeprenewal.egg-info/entry_points.txt
deeprenewal.egg-info/not-zip-safe
deeprenewal.egg-info/requires.txt
deeprenewal.egg-info/top_level.txt
deeprenewal/croston/__init__.py
deeprenewal/croston/_estimator.py
deeprenewal/croston/_predictor.py
deeprenewal/croston/croston.py
deeprenewal/deeprenewal/__init__.py
deeprenewal/deeprenewal/_estimator.py
deeprenewal/deeprenewal/_forecast_generator.py
deeprenewal/deeprenewal/_network.py
deeprenewal/deeprenewal/_sampler.py
deeprenewal/deeprenewal/_transforms.py
docs/apidocs.md
docs/authors.md
docs/contributing.md
docs/history.md
docs/index.md
docs/imgs/1.png
docs/imgs/Deep_Renewal.png
tests/__init__.py
tests/test_deeprenewal.py