Metadata-Version: 2.1
Name: deeprenewal
Version: 0.3.3
Summary: An implementation of the DeepRenewal Processes in GluonTS
Home-page: https://github.com/manujosephv/deeprenewal
Author: Manu Joseph
Author-email: manujosephv@gmail.com
License: MIT license
Keywords: deeprenewal
Platform: UNKNOWN
Classifier: Development Status :: 2 - Pre-Alpha
Classifier: Intended Audience :: Developers
Classifier: License :: OSI Approved :: MIT License
Classifier: Natural Language :: English
Classifier: Programming Language :: Python :: 3
Classifier: Programming Language :: Python :: 3.6
Classifier: Programming Language :: Python :: 3.7
Classifier: Programming Language :: Python :: 3.8
Requires-Python: >=3.6
